[
  {
    "full_name": "EthWorks/useDApp",
    "stargazers_count": 1016,
    "open_issues_count": 92,
    "forks_count": 247
  },
  {
    "full_name": "NoahZinsmeister/web3-react",
    "stargazers_count": 3424,
    "open_issues_count": 39,
    "forks_count": 851
  },
  {
    "full_name": "Web3Modal/web3modal",
    "stargazers_count": 2471,
    "open_issues_count": 151,
    "forks_count": 614
  },
  {
    "full_name": "microsoft/Web-Dev-For-Beginners",
    "stargazers_count": 45817,
    "open_issues_count": 4,
    "forks_count": 6662
  },
  {
    "full_name": "kamranahmedse/developer-roadmap",
    "stargazers_count": 191572,
    "open_issues_count": 128,
    "forks_count": 27622
  },
  {
    "full_name": "MunGell/awesome-for-beginners",
    "stargazers_count": 39538,
    "open_issues_count": 73,
    "forks_count": 5593
  },
  {
    "full_name": "practical-tutorials/project-based-learning",
    "stargazers_count": 65944,
    "open_issues_count": 19,
    "forks_count": 9948
  },
  {
    "full_name": "freeCodeCamp/freeCodeCamp",
    "stargazers_count": 343810,
    "open_issues_count": 148,
    "forks_count": 28427
  }
]