[
  {
    "full_name": "EthWorks/useDApp",
    "stargazers_count": 370,
    "open_issues_count": 37,
    "forks_count": 87
  },
  {
    "full_name": "NoahZinsmeister/web3-react",
    "stargazers_count": 1539,
    "open_issues_count": 111,
    "forks_count": 412
  },
  {
    "full_name": "Web3Modal/web3modal",
    "stargazers_count": 990,
    "open_issues_count": 114,
    "forks_count": 302
  },
  {
    "full_name": "microsoft/Web-Dev-For-Beginners",
    "stargazers_count": 34651,
    "open_issues_count": 6,
    "forks_count": 4741
  },
  {
    "full_name": "kamranahmedse/developer-roadmap",
    "stargazers_count": 170023,
    "open_issues_count": 83,
    "forks_count": 24515
  },
  {
    "full_name": "MunGell/awesome-for-beginners",
    "stargazers_count": 34357,
    "open_issues_count": 37,
    "forks_count": 5026
  },
  {
    "full_name": "practical-tutorials/project-based-learning",
    "stargazers_count": 55414,
    "open_issues_count": 23,
    "forks_count": 8594
  },
  {
    "full_name": "freeCodeCamp/freeCodeCamp",
    "stargazers_count": 329396,
    "open_issues_count": 152,
    "forks_count": 26501
  }
]