[
  {
    "full_name": "EthWorks/useDApp",
    "stargazers_count": 988,
    "open_issues_count": 105,
    "forks_count": 244
  },
  {
    "full_name": "NoahZinsmeister/web3-react",
    "stargazers_count": 3332,
    "open_issues_count": 33,
    "forks_count": 817
  },
  {
    "full_name": "Web3Modal/web3modal",
    "stargazers_count": 2402,
    "open_issues_count": 159,
    "forks_count": 596
  },
  {
    "full_name": "microsoft/Web-Dev-For-Beginners",
    "stargazers_count": 45126,
    "open_issues_count": 5,
    "forks_count": 6523
  },
  {
    "full_name": "kamranahmedse/developer-roadmap",
    "stargazers_count": 190309,
    "open_issues_count": 121,
    "forks_count": 27398
  },
  {
    "full_name": "MunGell/awesome-for-beginners",
    "stargazers_count": 39395,
    "open_issues_count": 64,
    "forks_count": 5587
  },
  {
    "full_name": "practical-tutorials/project-based-learning",
    "stargazers_count": 65411,
    "open_issues_count": 21,
    "forks_count": 9878
  },
  {
    "full_name": "freeCodeCamp/freeCodeCamp",
    "stargazers_count": 343315,
    "open_issues_count": 153,
    "forks_count": 28352
  }
]